icloud_todotxt/__init__.py
icloud_todotxt/main.py
icloud_todotxt-0.1.4.dist-info/entry_points.txt
icloud_todotxt-0.1.4.dist-info/LICENSE
icloud_todotxt-0.1.4.dist-info/WHEEL
icloud_todotxt-0.1.4.dist-info/METADATA
icloud_todotxt-0.1.4.dist-info/RECORD
