Metadata-Version: 2.1
Name: icloud-todotxt
Version: 0.1.4
Summary: Synchronize your local `todo.txt` with iCloud.
Home-page: https://github.com/DavidHeresy/icloud-todotxt
Author: David Härer
Author-email: david@familie-haerer.de
Requires-Python: >=3.9,<4.0
Classifier: Programming Language :: Python :: 3
Classifier: Programming Language :: Python :: 3.10
Classifier: Programming Language :: Python :: 3.9
Requires-Dist: pyicloud (>=1.0.0,<2.0.0)
Requires-Dist: typer (>=0.4.1,<0.5.0)
